casavo_log_formatter/__init__.py
casavo_log_formatter/formatters.py
casavo_log_formatter-1.0.3.dist-info/LICENSE.txt
casavo_log_formatter-1.0.3.dist-info/METADATA
casavo_log_formatter-1.0.3.dist-info/WHEEL
casavo_log_formatter-1.0.3.dist-info/top_level.txt
casavo_log_formatter-1.0.3.dist-info/RECORD
