Metadata-Version: 2.1
Name: casavo-log-formatter
Version: 1.0.3
Summary: A pre-configured JSON formatter for the Casavo logging format
Author-email: Casavo <tech.internals@casavo.com>
Maintainer-email: Casavo <tech.internals@casavo.com>
License: Copyright 2023 Casavo Management S.p.A.
Project-URL: Homepage, https://github.com/casavo/casavo-log-formatter
Project-URL: Bug Reports, https://github.com/casavo/casavo-log-formatter/issues
Project-URL: Source, https://github.com/casavo/casavo-log-formatter
Keywords: casavo,logging,json
Classifier: Development Status :: 5 - Production/Stable
Classifier: Intended Audience :: Developers
Classifier: Topic :: System :: Logging
Classifier: License :: OSI Approved :: MIT License
Classifier: Programming Language :: Python :: 3.9
Classifier: Programming Language :: Python :: 3.10
Classifier: Programming Language :: Python :: 3.11
Classifier: Programming Language :: Python :: 3 :: Only
Requires-Python: >=3.9
License-File: LICENSE.txt
Provides-Extra: dev
Requires-Dist: pip-tools ; extra == 'dev'
Requires-Dist: black ; extra == 'dev'
Requires-Dist: ruff ; extra == 'dev'
Requires-Dist: orjson ; extra == 'dev'
Requires-Dist: pre-commit ; extra == 'dev'
Requires-Dist: isort ; extra == 'dev'
Requires-Dist: nox ; extra == 'dev'
Requires-Dist: build ; extra == 'dev'
Requires-Dist: twine ; extra == 'dev'
Provides-Extra: orjson
Requires-Dist: orjson ; extra == 'orjson'
